Metadata-Version: 2.1
Name: beam-nuggets
Version: 0.18.1
Summary: Collection of transforms for the Apache beam python SDK.
Home-page: https://github.com/mohaseeb/beam-nuggets
Author: Mohamed Haseeb
Author-email: m@mohaseeb.com
License: UNKNOWN
Platform: UNKNOWN
Classifier: Programming Language :: Python
Classifier: Programming Language :: Python :: 3
Classifier: License :: OSI Approved :: MIT License
Classifier: Operating System :: OS Independent
Provides-Extra: dev
License-File: LICENSE
